bulkwhoisapi/__init__.py
bulkwhoisapi/client.py
bulkwhoisapi/version.py
bulkwhoisapi/exceptions/__init__.py
bulkwhoisapi/exceptions/error.py
bulkwhoisapi/models/__init__.py
bulkwhoisapi/models/response.py
bulkwhoisapi/net/__init__.py
bulkwhoisapi/net/http.py
bulk_whois_api-1.1.1.dist-info/AUTHORS.rst
bulk_whois_api-1.1.1.dist-info/LICENSE
bulk_whois_api-1.1.1.dist-info/METADATA
bulk_whois_api-1.1.1.dist-info/WHEEL
bulk_whois_api-1.1.1.dist-info/top_level.txt
bulk_whois_api-1.1.1.dist-info/RECORD
